pdfdocument/__init__.py
pdfdocument/document.py
pdfdocument/elements.py
pdfdocument/utils.py
pdfdocument-4.0.0.dist-info/LICENSE
pdfdocument-4.0.0.dist-info/METADATA
pdfdocument-4.0.0.dist-info/WHEEL
pdfdocument-4.0.0.dist-info/top_level.txt
pdfdocument-4.0.0.dist-info/RECORD
