Metadata-Version: 1.0
Name: pdfdocument
Version: 4.0.0
Summary: Programmatic wrapper around ReportLab.
Home-page: https://github.com/matthiask/pdfdocument/
Author: Matthias Kestenholz
Author-email: mk@feinheit.ch
License: UNKNOWN
Platform: UNKNOWN
